{
  "presentationTable": {
    "name": "Sites",
    "presentationColumns": [ {
        "name": "SiteID",
        "sourceLogicalColumn": "logicalColumn:TransactionalNorthwinds.Sites.SiteID"
      },
      {
        "name": "CustomerID",
        "sourceLogicalColumn": "logicalColumn:TransactionalNorthwinds.Sites.CustomerID"
      },
      {
        "name": "SiteName",
        "sourceLogicalColumn": "logicalColumn:TransactionalNorthwinds.Sites.SiteName"
      },
      {
        "name": "ContactName",
        "sourceLogicalColumn": "logicalColumn:TransactionalNorthwinds.Sites.ContactName"
      },
      {
        "name": "ContactTitle",
        "sourceLogicalColumn": "logicalColumn:TransactionalNorthwinds.Sites.ContactTitle"
      },
      {
        "name": "Address",
        "sourceLogicalColumn": "logicalColumn:TransactionalNorthwinds.Sites.Address"
      },
      {
        "name": "City",
        "sourceLogicalColumn": "logicalColumn:TransactionalNorthwinds.Sites.City"
      },
      {
        "name": "Region",
        "sourceLogicalColumn": "logicalColumn:TransactionalNorthwinds.Sites.Region"
      },
      {
        "name": "PostalCode",
        "sourceLogicalColumn": "logicalColumn:TransactionalNorthwinds.Sites.PostalCode"
      },
      {
        "name": "Country",
        "sourceLogicalColumn": "logicalColumn:TransactionalNorthwinds.Sites.Country"
      },
      {
        "name": "Phone",
        "sourceLogicalColumn": "logicalColumn:TransactionalNorthwinds.Sites.Phone"
      },
      {
        "name": "Fax",
        "sourceLogicalColumn": "logicalColumn:TransactionalNorthwinds.Sites.Fax"
      }
    ]
  }
}
