{
  "presentationTable": {
    "name": "EmployeeCity",
    "presentationColumns": [
      {
        "name": "City",
        "sourceLogicalColumn": "logicalColumn:SS-FilteredMetricsTesting.EmployeeCity.City"
      },
      {
        "name": "Region",
        "sourceLogicalColumn": "logicalColumn:SS-FilteredMetricsTesting.EmployeeCity.Region"
      },
      {
        "name": "Country",
        "sourceLogicalColumn": "logicalColumn:SS-FilteredMetricsTesting.EmployeeCity.Country"
      },
      {
        "name": "Revenue",
        "sourceLogicalColumn": "logicalColumn:SS-FilteredMetricsTesting.EmployeeCity.Revenue"
      },
      {
        "name": "QtySold",
        "sourceLogicalColumn": "logicalColumn:SS-FilteredMetricsTesting.EmployeeCity.QtySold"
      }
    ]
  }
}
