{
  "presentationTable": {
    "name": "Employee",
    "presentationColumns": [
      {
        "name": "EmployeeID",
        "sourceLogicalColumn": "logicalColumn:SnowflakeSales_subrequest.Employee.EmployeeID"
      },
      {
        "name": "LastName",
        "sourceLogicalColumn": "logicalColumn:SnowflakeSales_subrequest.Employee.LastName"
      },
      {
        "name": "FirstName",
        "sourceLogicalColumn": "logicalColumn:SnowflakeSales_subrequest.Employee.FirstName"
      },
      {
        "name": "Title",
        "sourceLogicalColumn": "logicalColumn:SnowflakeSales_subrequest.Employee.Title"
      },
      {
        "name": "TitleOfCourtesy",
        "sourceLogicalColumn": "logicalColumn:SnowflakeSales_subrequest.Employee.TitleOfCourtesy"
      },
      {
        "name": "BirthDate",
        "sourceLogicalColumn": "logicalColumn:SnowflakeSales_subrequest.Employee.BirthDate"
      },
      {
        "name": "HireDate",
        "sourceLogicalColumn": "logicalColumn:SnowflakeSales_subrequest.Employee.HireDate"
      },
      {
        "name": "PostalCode",
        "sourceLogicalColumn": "logicalColumn:SnowflakeSales_subrequest.Employee.PostalCode"
      },
      {
        "name": "Address",
        "sourceLogicalColumn": "logicalColumn:SnowflakeSales_subrequest.Employee.Address"
      },
      {
        "name": "HomePhone",
        "sourceLogicalColumn": "logicalColumn:SnowflakeSales_subrequest.Employee.HomePhone"
      },
      {
        "name": "Extension",
        "sourceLogicalColumn": "logicalColumn:SnowflakeSales_subrequest.Employee.Extension"
      },
      {
        "name": "Notes",
        "sourceLogicalColumn": "logicalColumn:SnowflakeSales_subrequest.Employee.Notes"
      },
      {
        "name": "ReportsTo",
        "sourceLogicalColumn": "logicalColumn:SnowflakeSales_subrequest.Employee.ReportsTo"
      },
      {
        "name": "Revenue",
        "sourceLogicalColumn": "logicalColumn:SnowflakeSales_subrequest.Employee.Revenue"
      },
      {
        "name": "QtySold",
        "sourceLogicalColumn": "logicalColumn:SnowflakeSales_subrequest.Employee.QtySold"
      },
      {
        "name": "Country",
        "sourceLogicalColumn": "logicalColumn:SnowflakeSales_subrequest.Employee.Country"
      },
      {
        "name": "Region",
        "sourceLogicalColumn": "logicalColumn:SnowflakeSales_subrequest.Employee.Region"
      },
      {
        "name": "City",
        "sourceLogicalColumn": "logicalColumn:SnowflakeSales_subrequest.Employee.City"
      },
      {
        "name": "BirthMonth",
        "sourceLogicalColumn": "logicalColumn:SnowflakeSales_subrequest.Employee.BirthMonth"
      }
    ]
  }
}
