{
  "logicalTable": {
    "name": "Reseller Order Frequency",
    "type": "DIMENSION",
    "logicalColumns": [ {
        "name": "[Reseller].[Reseller Order Frequency].[(All)]",
        "dataType": "VARCHAR",
        "descriptorColumn": "[Reseller].[Reseller Order Frequency].[(All)] - Member Key",
        "logicalColumnSource": {
          "derivedFrom": "PHYSICAL_COLUMNS",
          "physicalMappings": [ {
              "logicalTableSource": "Adventure Works",
              "physicalExpression": {
                "expressionTemplate": "%1",
                "expressionObjects": [
                  "physicalCubeColumn:Adventure Works DW.Adventure Works.[Reseller].[Reseller Order Frequency].[(All)]"
                ]
              }
            }
          ]
        }
      },
      {
        "name": "[Reseller].[Reseller Order Frequency].[(All)] - Member Key",
        "dataType": "VARCHAR",
        "logicalColumnSource": {
          "derivedFrom": "PHYSICAL_COLUMNS",
          "physicalMappings": [ {
              "logicalTableSource": "Adventure Works",
              "physicalExpression": {
                "expressionTemplate": "%1",
                "expressionObjects": [
                  "physicalCubeColumn:Adventure Works DW.Adventure Works.[Reseller].[Reseller Order Frequency].[(All)] - Member Key"
                ]
              }
            }
          ]
        }
      },
      {
        "name": "Address#6",
        "dataType": "VARCHAR",
        "logicalColumnSource": {
          "derivedFrom": "PHYSICAL_COLUMNS",
          "physicalMappings": [ {
              "logicalTableSource": "Adventure Works",
              "physicalExpression": {
                "expressionTemplate": "%1",
                "expressionObjects": [
                  "physicalCubeColumn:Adventure Works DW.Adventure Works.Address#6"
                ]
              }
            }
          ]
        }
      },
      {
        "name": "Annual Revenue#3",
        "dataType": "VARCHAR",
        "logicalColumnSource": {
          "derivedFrom": "PHYSICAL_COLUMNS",
          "physicalMappings": [ {
              "logicalTableSource": "Adventure Works",
              "physicalExpression": {
                "expressionTemplate": "%1",
                "expressionObjects": [
                  "physicalCubeColumn:Adventure Works DW.Adventure Works.Annual Revenue#3"
                ]
              }
            }
          ]
        }
      },
      {
        "name": "Annual Sales#3",
        "dataType": "VARCHAR",
        "logicalColumnSource": {
          "derivedFrom": "PHYSICAL_COLUMNS",
          "physicalMappings": [ {
              "logicalTableSource": "Adventure Works",
              "physicalExpression": {
                "expressionTemplate": "%1",
                "expressionObjects": [
                  "physicalCubeColumn:Adventure Works DW.Adventure Works.Annual Sales#3"
                ]
              }
            }
          ]
        }
      },
      {
        "name": "Bank Name#4",
        "dataType": "VARCHAR",
        "logicalColumnSource": {
          "derivedFrom": "PHYSICAL_COLUMNS",
          "physicalMappings": [ {
              "logicalTableSource": "Adventure Works",
              "physicalExpression": {
                "expressionTemplate": "%1",
                "expressionObjects": [
                  "physicalCubeColumn:Adventure Works DW.Adventure Works.Bank Name#4"
                ]
              }
            }
          ]
        }
      },
      {
        "name": "Business Type#3",
        "dataType": "VARCHAR",
        "logicalColumnSource": {
          "derivedFrom": "PHYSICAL_COLUMNS",
          "physicalMappings": [ {
              "logicalTableSource": "Adventure Works",
              "physicalExpression": {
                "expressionTemplate": "%1",
                "expressionObjects": [
                  "physicalCubeColumn:Adventure Works DW.Adventure Works.Business Type#3"
                ]
              }
            }
          ]
        }
      },
      {
        "name": "First Order Year#3",
        "dataType": "VARCHAR",
        "logicalColumnSource": {
          "derivedFrom": "PHYSICAL_COLUMNS",
          "physicalMappings": [ {
              "logicalTableSource": "Adventure Works",
              "physicalExpression": {
                "expressionTemplate": "%1",
                "expressionObjects": [
                  "physicalCubeColumn:Adventure Works DW.Adventure Works.First Order Year#3"
                ]
              }
            }
          ]
        }
      },
      {
        "name": "KEY0#333",
        "dataType": "VARCHAR",
        "logicalColumnSource": {
          "derivedFrom": "PHYSICAL_COLUMNS",
          "physicalMappings": [ {
              "logicalTableSource": "Adventure Works",
              "physicalExpression": {
                "expressionTemplate": "%1",
                "expressionObjects": [
                  "physicalCubeColumn:Adventure Works DW.Adventure Works.KEY0#333"
                ]
              }
            }
          ]
        }
      },
      {
        "name": "KEY0#334",
        "dataType": "VARCHAR",
        "logicalColumnSource": {
          "derivedFrom": "PHYSICAL_COLUMNS",
          "physicalMappings": [ {
              "logicalTableSource": "Adventure Works",
              "physicalExpression": {
                "expressionTemplate": "%1",
                "expressionObjects": [
                  "physicalCubeColumn:Adventure Works DW.Adventure Works.KEY0#334"
                ]
              }
            }
          ]
        }
      },
      {
        "name": "KEY0#335",
        "dataType": "VARCHAR",
        "logicalColumnSource": {
          "derivedFrom": "PHYSICAL_COLUMNS",
          "physicalMappings": [ {
              "logicalTableSource": "Adventure Works",
              "physicalExpression": {
                "expressionTemplate": "%1",
                "expressionObjects": [
                  "physicalCubeColumn:Adventure Works DW.Adventure Works.KEY0#335"
                ]
              }
            }
          ]
        }
      },
      {
        "name": "Last Order Year#3",
        "dataType": "VARCHAR",
        "logicalColumnSource": {
          "derivedFrom": "PHYSICAL_COLUMNS",
          "physicalMappings": [ {
              "logicalTableSource": "Adventure Works",
              "physicalExpression": {
                "expressionTemplate": "%1",
                "expressionObjects": [
                  "physicalCubeColumn:Adventure Works DW.Adventure Works.Last Order Year#3"
                ]
              }
            }
          ]
        }
      },
      {
        "name": "MEMBER_VALUE#333",
        "dataType": "VARCHAR",
        "logicalColumnSource": {
          "derivedFrom": "PHYSICAL_COLUMNS",
          "physicalMappings": [ {
              "logicalTableSource": "Adventure Works",
              "physicalExpression": {
                "expressionTemplate": "%1",
                "expressionObjects": [
                  "physicalCubeColumn:Adventure Works DW.Adventure Works.MEMBER_VALUE#333"
                ]
              }
            }
          ]
        }
      },
      {
        "name": "MEMBER_VALUE#334",
        "dataType": "VARCHAR",
        "logicalColumnSource": {
          "derivedFrom": "PHYSICAL_COLUMNS",
          "physicalMappings": [ {
              "logicalTableSource": "Adventure Works",
              "physicalExpression": {
                "expressionTemplate": "%1",
                "expressionObjects": [
                  "physicalCubeColumn:Adventure Works DW.Adventure Works.MEMBER_VALUE#334"
                ]
              }
            }
          ]
        }
      },
      {
        "name": "MEMBER_VALUE#335",
        "dataType": "VARCHAR",
        "logicalColumnSource": {
          "derivedFrom": "PHYSICAL_COLUMNS",
          "physicalMappings": [ {
              "logicalTableSource": "Adventure Works",
              "physicalExpression": {
                "expressionTemplate": "%1",
                "expressionObjects": [
                  "physicalCubeColumn:Adventure Works DW.Adventure Works.MEMBER_VALUE#335"
                ]
              }
            }
          ]
        }
      },
      {
        "name": "Min Payment Amount#3",
        "dataType": "VARCHAR",
        "logicalColumnSource": {
          "derivedFrom": "PHYSICAL_COLUMNS",
          "physicalMappings": [ {
              "logicalTableSource": "Adventure Works",
              "physicalExpression": {
                "expressionTemplate": "%1",
                "expressionObjects": [
                  "physicalCubeColumn:Adventure Works DW.Adventure Works.Min Payment Amount#3"
                ]
              }
            }
          ]
        }
      },
      {
        "name": "Min Payment Type#3",
        "dataType": "VARCHAR",
        "logicalColumnSource": {
          "derivedFrom": "PHYSICAL_COLUMNS",
          "physicalMappings": [ {
              "logicalTableSource": "Adventure Works",
              "physicalExpression": {
                "expressionTemplate": "%1",
                "expressionObjects": [
                  "physicalCubeColumn:Adventure Works DW.Adventure Works.Min Payment Type#3"
                ]
              }
            }
          ]
        }
      },
      {
        "name": "NAME#265",
        "dataType": "VARCHAR",
        "logicalColumnSource": {
          "derivedFrom": "PHYSICAL_COLUMNS",
          "physicalMappings": [ {
              "logicalTableSource": "Adventure Works",
              "physicalExpression": {
                "expressionTemplate": "%1",
                "expressionObjects": [
                  "physicalCubeColumn:Adventure Works DW.Adventure Works.NAME#265"
                ]
              }
            }
          ]
        }
      },
      {
        "name": "NAME#266",
        "dataType": "VARCHAR",
        "logicalColumnSource": {
          "derivedFrom": "PHYSICAL_COLUMNS",
          "physicalMappings": [ {
              "logicalTableSource": "Adventure Works",
              "physicalExpression": {
                "expressionTemplate": "%1",
                "expressionObjects": [
                  "physicalCubeColumn:Adventure Works DW.Adventure Works.NAME#266"
                ]
              }
            }
          ]
        }
      },
      {
        "name": "NAME#267",
        "dataType": "VARCHAR",
        "logicalColumnSource": {
          "derivedFrom": "PHYSICAL_COLUMNS",
          "physicalMappings": [ {
              "logicalTableSource": "Adventure Works",
              "physicalExpression": {
                "expressionTemplate": "%1",
                "expressionObjects": [
                  "physicalCubeColumn:Adventure Works DW.Adventure Works.NAME#267"
                ]
              }
            }
          ]
        }
      },
      {
        "name": "Number of Employees#3",
        "dataType": "VARCHAR",
        "logicalColumnSource": {
          "derivedFrom": "PHYSICAL_COLUMNS",
          "physicalMappings": [ {
              "logicalTableSource": "Adventure Works",
              "physicalExpression": {
                "expressionTemplate": "%1",
                "expressionObjects": [
                  "physicalCubeColumn:Adventure Works DW.Adventure Works.Number of Employees#3"
                ]
              }
            }
          ]
        }
      },
      {
        "name": "Order Frequency - Member Key#1",
        "dataType": "VARCHAR",
        "logicalColumnSource": {
          "derivedFrom": "PHYSICAL_COLUMNS",
          "physicalMappings": [ {
              "logicalTableSource": "Adventure Works",
              "physicalExpression": {
                "expressionTemplate": "%1",
                "expressionObjects": [
                  "physicalCubeColumn:Adventure Works DW.Adventure Works.Order Frequency - Member Key#1"
                ]
              }
            }
          ]
        }
      },
      {
        "name": "Order Frequency#3",
        "dataType": "VARCHAR",
        "descriptorColumn": "Order Frequency - Member Key#1",
        "logicalColumnSource": {
          "derivedFrom": "PHYSICAL_COLUMNS",
          "physicalMappings": [ {
              "logicalTableSource": "Adventure Works",
              "physicalExpression": {
                "expressionTemplate": "%1",
                "expressionObjects": [
                  "physicalCubeColumn:Adventure Works DW.Adventure Works.Order Frequency#3"
                ]
              }
            }
          ]
        }
      },
      {
        "name": "Order Frequency#4",
        "dataType": "VARCHAR",
        "logicalColumnSource": {
          "derivedFrom": "PHYSICAL_COLUMNS",
          "physicalMappings": [ {
              "logicalTableSource": "Adventure Works",
              "physicalExpression": {
                "expressionTemplate": "%1",
                "expressionObjects": [
                  "physicalCubeColumn:Adventure Works DW.Adventure Works.Order Frequency#4"
                ]
              }
            }
          ]
        }
      },
      {
        "name": "Order Month#3",
        "dataType": "VARCHAR",
        "logicalColumnSource": {
          "derivedFrom": "PHYSICAL_COLUMNS",
          "physicalMappings": [ {
              "logicalTableSource": "Adventure Works",
              "physicalExpression": {
                "expressionTemplate": "%1",
                "expressionObjects": [
                  "physicalCubeColumn:Adventure Works DW.Adventure Works.Order Month#3"
                ]
              }
            }
          ]
        }
      },
      {
        "name": "Phone#14",
        "dataType": "VARCHAR",
        "logicalColumnSource": {
          "derivedFrom": "PHYSICAL_COLUMNS",
          "physicalMappings": [ {
              "logicalTableSource": "Adventure Works",
              "physicalExpression": {
                "expressionTemplate": "%1",
                "expressionObjects": [
                  "physicalCubeColumn:Adventure Works DW.Adventure Works.Phone#14"
                ]
              }
            }
          ]
        }
      },
      {
        "name": "Product Line#8",
        "dataType": "VARCHAR",
        "logicalColumnSource": {
          "derivedFrom": "PHYSICAL_COLUMNS",
          "physicalMappings": [ {
              "logicalTableSource": "Adventure Works",
              "physicalExpression": {
                "expressionTemplate": "%1",
                "expressionObjects": [
                  "physicalCubeColumn:Adventure Works DW.Adventure Works.Product Line#8"
                ]
              }
            }
          ]
        }
      },
      {
        "name": "Reseller - Member Key#2",
        "dataType": "VARCHAR",
        "logicalColumnSource": {
          "derivedFrom": "PHYSICAL_COLUMNS",
          "physicalMappings": [ {
              "logicalTableSource": "Adventure Works",
              "physicalExpression": {
                "expressionTemplate": "%1",
                "expressionObjects": [
                  "physicalCubeColumn:Adventure Works DW.Adventure Works.Reseller - Member Key#2"
                ]
              }
            }
          ]
        }
      },
      {
        "name": "Reseller#2",
        "dataType": "VARCHAR",
        "descriptorColumn": "Reseller - Member Key#2",
        "logicalColumnSource": {
          "derivedFrom": "PHYSICAL_COLUMNS",
          "physicalMappings": [ {
              "logicalTableSource": "Adventure Works",
              "physicalExpression": {
                "expressionTemplate": "%1",
                "expressionObjects": [
                  "physicalCubeColumn:Adventure Works DW.Adventure Works.Reseller#2"
                ]
              }
            }
          ]
        }
      },
      {
        "name": "Year Opened#2",
        "dataType": "VARCHAR",
        "logicalColumnSource": {
          "derivedFrom": "PHYSICAL_COLUMNS",
          "physicalMappings": [ {
              "logicalTableSource": "Adventure Works",
              "physicalExpression": {
                "expressionTemplate": "%1",
                "expressionObjects": [
                  "physicalCubeColumn:Adventure Works DW.Adventure Works.Year Opened#2"
                ]
              }
            }
          ]
        }
      }
    ],
    "logicalTableSources": [ {
        "name": "Adventure Works",
        "tableMapping": {
          "tables": [
            "physicalTable:Adventure Works DW.Adventure Works"
          ],
          "logicalTableSourceJoins": [
            {
            }
          ]
        },
        "dataGranularity": [
          "logicalLevel:Adventure Works DW.Reseller Order Frequency.Reseller"
        ]
      }
    ],
    "hierarchyType": "LEVEL_BASED",
    "levelBasedHierarchy": {
      "defaultRootLevel": "[Reseller].[Reseller Order Frequency].[(All)]",
      "logicalLevels": [
        {
          "name": "[Reseller].[Reseller Order Frequency].[(All)]",
          "aggregateToHigherLevel": true,
          "numberOfElements": 1,
          "primaryColumns": [
            "[Reseller].[Reseller Order Frequency].[(All)] - Member Key"
          ]
        },
        {
          "name": "Order Frequency",
          "aggregateToHigherLevel": true,
          "numberOfElements": 1,
          "primaryColumns": [
            "Order Frequency - Member Key#1"
          ]
        },
        {
          "name": "Reseller",
          "aggregateToHigherLevel": true,
          "numberOfElements": 1,
          "primaryColumns": [
            "Reseller - Member Key#2"
          ]
        }
      ],
      "logicalHierarchies": [ {
          "name": "Reseller Order Frequency",
          "levels": [ "[Reseller].[Reseller Order Frequency].[(All)]", "Order Frequency", "Reseller" ]
        }
      ]
    }
  }
}
