{
  "logicalTable": {
    "name": "Employees",
    "type": "DIMENSION",
    "logicalColumns": [ {
        "name": "Address",
        "dataType": "VARCHAR",
        "logicalColumnSource": {
          "derivedFrom": "PHYSICAL_COLUMNS",
          "physicalMappings": [ {
              "logicalTableSource": "Employees",
              "physicalExpression": {
                "expressionTemplate": "%1",
                "expressionObjects": [
                  "physicalColumn:CacheSecurityTesting.Employees.Address"
                ]
              }
            }
          ]
        }
      },
      {
        "name": "BirthDate",
        "dataType": "DATETIME",
        "logicalColumnSource": {
          "derivedFrom": "PHYSICAL_COLUMNS",
          "physicalMappings": [ {
              "logicalTableSource": "Employees",
              "physicalExpression": {
                "expressionTemplate": "%1",
                "expressionObjects": [
                  "physicalColumn:CacheSecurityTesting.Employees.BirthDate"
                ]
              }
            }
          ]
        }
      },
      {
        "name": "City",
        "dataType": "CHAR",
        "logicalColumnSource": {
          "derivedFrom": "PHYSICAL_COLUMNS",
          "physicalMappings": [ {
              "logicalTableSource": "Employees",
              "physicalExpression": {
                "expressionTemplate": "%1",
                "expressionObjects": [
                  "physicalColumn:CacheSecurityTesting.Employees.City"
                ]
              }
            }
          ]
        }
      },
      {
        "name": "Country",
        "dataType": "CHAR",
        "logicalColumnSource": {
          "derivedFrom": "PHYSICAL_COLUMNS",
          "physicalMappings": [ {
              "logicalTableSource": "Employees",
              "physicalExpression": {
                "expressionTemplate": "%1",
                "expressionObjects": [
                  "physicalColumn:CacheSecurityTesting.Employees.Country"
                ]
              }
            }
          ]
        }
      },
      {
        "name": "EmployeeID",
        "dataType": "SMALLINT",
        "logicalColumnSource": {
          "derivedFrom": "PHYSICAL_COLUMNS",
          "physicalMappings": [ {
              "logicalTableSource": "Employees",
              "physicalExpression": {
                "expressionTemplate": "%1",
                "expressionObjects": [
                  "physicalColumn:CacheSecurityTesting.Employees.EmployeeID"
                ]
              }
            }
          ]
        }
      },
      {
        "name": "Extension",
        "dataType": "CHAR",
        "logicalColumnSource": {
          "derivedFrom": "PHYSICAL_COLUMNS",
          "physicalMappings": [ {
              "logicalTableSource": "Employees",
              "physicalExpression": {
                "expressionTemplate": "%1",
                "expressionObjects": [
                  "physicalColumn:CacheSecurityTesting.Employees.Extension"
                ]
              }
            }
          ]
        }
      },
      {
        "name": "FirstName",
        "dataType": "CHAR",
        "logicalColumnSource": {
          "derivedFrom": "PHYSICAL_COLUMNS",
          "physicalMappings": [ {
              "logicalTableSource": "Employees",
              "physicalExpression": {
                "expressionTemplate": "%1",
                "expressionObjects": [
                  "physicalColumn:CacheSecurityTesting.Employees.FirstName"
                ]
              }
            }
          ]
        }
      },
      {
        "name": "HireDate",
        "dataType": "DATETIME",
        "logicalColumnSource": {
          "derivedFrom": "PHYSICAL_COLUMNS",
          "physicalMappings": [ {
              "logicalTableSource": "Employees",
              "physicalExpression": {
                "expressionTemplate": "%1",
                "expressionObjects": [
                  "physicalColumn:CacheSecurityTesting.Employees.HireDate"
                ]
              }
            }
          ]
        }
      },
      {
        "name": "HomePhone",
        "dataType": "CHAR",
        "logicalColumnSource": {
          "derivedFrom": "PHYSICAL_COLUMNS",
          "physicalMappings": [ {
              "logicalTableSource": "Employees",
              "physicalExpression": {
                "expressionTemplate": "%1",
                "expressionObjects": [
                  "physicalColumn:CacheSecurityTesting.Employees.HomePhone"
                ]
              }
            }
          ]
        }
      },
      {
        "name": "LastName",
        "dataType": "CHAR",
        "logicalColumnSource": {
          "derivedFrom": "PHYSICAL_COLUMNS",
          "physicalMappings": [ {
              "logicalTableSource": "Employees",
              "physicalExpression": {
                "expressionTemplate": "%1",
                "expressionObjects": [
                  "physicalColumn:CacheSecurityTesting.Employees.LastName"
                ]
              }
            }
          ]
        }
      },
      {
        "name": "Notes",
        "dataType": "VARCHAR",
        "logicalColumnSource": {
          "derivedFrom": "PHYSICAL_COLUMNS",
          "physicalMappings": [ {
              "logicalTableSource": "Employees",
              "physicalExpression": {
                "expressionTemplate": "%1",
                "expressionObjects": [
                  "physicalColumn:CacheSecurityTesting.Employees.Notes"
                ]
              }
            }
          ]
        }
      },
      {
        "name": "PostalCode",
        "dataType": "CHAR",
        "logicalColumnSource": {
          "derivedFrom": "PHYSICAL_COLUMNS",
          "physicalMappings": [ {
              "logicalTableSource": "Employees",
              "physicalExpression": {
                "expressionTemplate": "%1",
                "expressionObjects": [
                  "physicalColumn:CacheSecurityTesting.Employees.PostalCode"
                ]
              }
            }
          ]
        }
      },
      {
        "name": "Region",
        "dataType": "CHAR",
        "logicalColumnSource": {
          "derivedFrom": "PHYSICAL_COLUMNS",
          "physicalMappings": [ {
              "logicalTableSource": "Employees",
              "physicalExpression": {
                "expressionTemplate": "%1",
                "expressionObjects": [
                  "physicalColumn:CacheSecurityTesting.Employees.Region"
                ]
              }
            }
          ]
        }
      },
      {
        "name": "ReportsTo",
        "dataType": "SMALLINT",
        "logicalColumnSource": {
          "derivedFrom": "PHYSICAL_COLUMNS",
          "physicalMappings": [ {
              "logicalTableSource": "Employees",
              "physicalExpression": {
                "expressionTemplate": "%1",
                "expressionObjects": [
                  "physicalColumn:CacheSecurityTesting.Employees.ReportsTo"
                ]
              }
            }
          ]
        }
      },
      {
        "name": "Title",
        "dataType": "VARCHAR",
        "logicalColumnSource": {
          "derivedFrom": "PHYSICAL_COLUMNS",
          "physicalMappings": [ {
              "logicalTableSource": "Employees",
              "physicalExpression": {
                "expressionTemplate": "%1",
                "expressionObjects": [
                  "physicalColumn:CacheSecurityTesting.Employees.Title"
                ]
              }
            }
          ]
        }
      },
      {
        "name": "TitleOfCourtesy",
        "dataType": "VARCHAR",
        "logicalColumnSource": {
          "derivedFrom": "PHYSICAL_COLUMNS",
          "physicalMappings": [ {
              "logicalTableSource": "Employees",
              "physicalExpression": {
                "expressionTemplate": "%1",
                "expressionObjects": [
                  "physicalColumn:CacheSecurityTesting.Employees.TitleOfCourtesy"
                ]
              }
            }
          ]
        }
      }
    ],
    "logicalTableSources": [ {
        "name": "Employees",
        "tableMapping": {
          "tables": [
            "physicalTable:CacheSecurityTesting.Employees"
          ],
          "logicalTableSourceJoins": [
            {
            }
          ]
        }
      }
    ]
  }
}
